0526/ex/block.sv
module block (D,Clk,X,Y) ;
    input D,Clk;
    output reg [3:0] X,Y;
    integer i;

    always@ (posedge Clk) begin
        for(i=3;i>0;i=i-1) begin 
            X[i] = X[i-1];
        end

        
        for (i = 1; i<=3; i=i+1) begin
            Y[i] <= Y[i-1];
        end

        X[0] = D ;
        Y[0] <= D;
    end
endmodule

0526/ex/testbenach.sv
`timescale 1ns/1ns
module Test();

    reg clk,D;
    wire [3:0] Q1,Q2;

    block uut(
        .D(D),.Clk(clk),.X(Q1),.Y(Q2)
    );

    initial begin
        forever begin
            clk = !clk;
            #100;
        end
    end

    initial begin
        clk = 1'b0;D = 1'b0;
        #100;
        D = !D;
        #200;
        D = !D;
        #200;
        D = !D;
        #200;
        D = !D;
        #200;
        D = !D;
        #400;
        D = !D;
        #400;
        D = !D;
        #400;
    end
    initial begin
        $display("Starting Testbench");
        #2200;
        $finish;
    end

    initial begin
        $dumpfile("dump.vcd");
        $dumpvars(0);
    end

endmodule

0526/ex/dump.vcd
$date
	Thu May 25 22:54:16 2023
$end
$version
	Icarus Verilog
$end
$timescale
	1ns
$end
$scope module Test $end
$var wire 4 ! Q2 [3:0] $end
$var wire 4 " Q1 [3:0] $end
$var reg 1 # D $end
$var reg 1 $ clk $end
$scope module uut $end
$var wire 1 $ Clk $end
$var wire 1 # D $end
$var reg 4 % X [3:0] $end
$var reg 4 & Y [3:0] $end
$var integer 32 ' i [31:0] $end
$upscope $end
$upscope $end
$enddefinitions $end
$comment Show the parameter values. $end
$dumpall
$end
#0
$dumpvars
bx '
bx &
bx %
0$
0#
bx "
bx !
$end
#100
bx1 !
bx1 &
bx1 "
bx1 %
b100 '
1#
1$
#200
0$
#300
bx10 !
bx10 &
bx10 "
bx10 %
b100 '
1$
0#
#400
0$
#500
bx101 !
bx101 &
bx101 "
bx101 %
b100 '
1$
1#
#600
0$
#700
b1010 !
b1010 &
b1010 "
b1010 %
b100 '
1$
0#
#800
0$
#900
b101 !
b101 &
b101 "
b101 %
b100 '
1$
1#
#1000
0$
#1100
b1011 !
b1011 &
b1011 "
b1011 %
b100 '
1$
#1200
0$
#1300
b110 !
b110 &
b110 "
b110 %
b100 '
1$
0#
#1400
0$
#1500
b1100 !
b1100 &
b1100 "
b1100 %
b100 '
1$
#1600
0$
#1700
b1001 !
b1001 &
b1001 "
b1001 %
b100 '
1$
1#
#1800
0$
#1900
b11 !
b11 &
b11 "
b11 %
b100 '
1$
#2000
0$
#2100
b111 !
b111 &
b111 "
b111 %
b100 '
1$
