0526/final_exam/design.sv
module Question1 (Clk,D,Q1);
    input Clk,D;
    output reg [3:0] Q1;
    integer i;

    always @(posedge Clk) begin
        for (i = 3; i>0; i=i-1) begin
            Q1[i]=Q1[i-1];
        end
        Q1[0]=D;
    end
endmodule
module Question2 (Clk,D,Q2);
    input Clk,D;
    output reg [3:0] Q2;
    integer i;

    always @(posedge Clk) begin
        for (i = 1; i<=3; i=i+1) begin
            Q2[i] <=Q2[i-1];
        end
        Q2[0]=D;
    end
endmodule

0526/final_exam/testbench2.sv
`timescale 1ns/1ns
module Test();

    reg D,Clk;
    wire [3:0]Q1,Q2;
    Question2 test2(
        .Clk(Clk),.D(D),.Q2(Q2)
    );


    initial begin
    forever begin
        Clk = !Clk;
        #100;
    end
    end
    initial begin
        D=1'b0;Clk=1'b0;
        #100;
        D=!D;
        #200;
        D=!D;
        #200;
        D=!D;
        #200;
        D=!D;
        #200;
        D=!D;
        #400;
        D=!D;
        #400;
        D=!D;
        #400;
    end
    initial begin
        $display("Starting Testbench");
        #2200;
        $finish;
    end

    initial begin
        $dumpfile("dump.vcd");
        $dumpvars(0);
    end

endmodule

0526/final_exam/dump.vcd
$date
	Fri May 26 15:26:32 2023
$end
$version
	Icarus Verilog
$end
$timescale
	1ns
$end
$scope module Test $end
$var wire 4 ! Q2 [3:0] $end
$var reg 1 " Clk $end
$var reg 1 # D $end
$scope module test2 $end
$var wire 1 " Clk $end
$var wire 1 # D $end
$var reg 4 $ Q2 [3:0] $end
$var integer 32 % i [31:0] $end
$upscope $end
$upscope $end
$enddefinitions $end
$comment Show the parameter values. $end
$dumpall
$end
#0
$dumpvars
bx %
bx $
0#
0"
bx !
$end
#100
bx1 !
bx1 $
b100 %
1#
1"
#200
0"
#300
bx10 !
bx10 $
b100 %
1"
0#
#400
0"
#500
bx101 !
bx101 $
b100 %
1"
1#
#600
0"
#700
b1010 !
b1010 $
b100 %
1"
0#
#800
0"
#900
b101 !
b101 $
b100 %
1"
1#
#1000
0"
#1100
b1011 !
b1011 $
b100 %
1"
#1200
0"
#1300
b110 !
b110 $
b100 %
1"
0#
#1400
0"
#1500
b1100 !
b1100 $
b100 %
1"
#1600
0"
#1700
b1001 !
b1001 $
b100 %
1"
1#
#1800
0"
#1900
b11 !
b11 $
b100 %
1"
#2000
0"
#2100
b111 !
b111 $
b100 %
1"
