pratice/gate.sv
module Gate1 (
    input[3:0] A,input[3:0] B,input[3:0] C,output reg [3:0] X
);
    
    always @(*) begin
    if (A>=B && A>=C)
        assign X = A;
    else if (B>=A && B>=C)
        assign X = B;
    else 
        assign X = C;
    end

endmodule

// module Gate1(input [3:0] A, input [3:0] B, input [3:0] C, output reg [3:0] X);
//     always @(*)
//     begin
//         if(A >= B && A >= C)
//             X = A;
//         else if(B >= A && B >= C)
//             X = B;
//         else
//             X = C;
//     end
// endmodule

pratice/testbench.sv
`timescale 1ns/1ns
module Practice();

    reg[3:0] A,B,C;
    wire[3:0] X;

    Gate1 uut(
        .A(A),.B(B),.C(C),.X(X)
    );

    initial begin
        A = 3 ; B = 5 ; C = 41;
        #100;
        A = 1'b0 ; B = 1'b0 ; C = 2'b2;
        #100;
        A = 1'b0 ; B = 1'b1 ; C = 1'b0;
        #100;
        A = 1'b0 ; B = 1'b1 ; C = 1'b1;
        #100;
        A = 1'b1 ; B = 1'b0 ; C = 1'b0;
        #100;
        A = 1'b1 ; B = 1'b0 ; C = 1'b1;
        #100;
        A = 1'b1 ; B = 1'b1 ; C = 1'b0;
        #100;
        A = 1'b1 ; B = 1'b1 ; C = 1'b1;
        #100;
    end
    initial begin
        $display("Starting Testbench");
        #800;
        $finish;
    end

    initial begin
        $dumpfile("dump.vcd");
        $dumpvars(0);
    end

endmodule

pratice/dump.vcd
$date
	Fri May 12 23:21:50 2023
$end
$version
	Icarus Verilog
$end
$timescale
	1ns
$end
$scope module Practice $end
$var wire 4 ! X [3:0] $end
$var reg 4 " A [3:0] $end
$var reg 4 # B [3:0] $end
$var reg 4 $ C [3:0] $end
$scope module uut $end
$var wire 4 % A [3:0] $end
$var wire 4 & B [3:0] $end
$var wire 4 ' C [3:0] $end
$var reg 4 ( X [3:0] $end
$upscope $end
$upscope $end
$enddefinitions $end
$comment Show the parameter values. $end
$dumpall
$end
#0
$dumpvars
b1001 (
b1001 '
b101 &
b11 %
b1001 $
b101 #
b11 "
b1001 !
$end
#100
b1 !
b1 (
b1 $
b1 '
b0 #
b0 &
b0 "
b0 %
#200
b1 !
b1 (
b0 $
b0 '
b1 #
b1 &
#300
b1 $
b1 '
#400
b0 $
b0 '
b1 !
b1 (
b0 #
b0 &
b1 "
b1 %
#500
b1 $
b1 '
#600
b0 $
b0 '
b1 #
b1 &
#700
b1 $
b1 '
